iconfonts.py
markdown_iconfonts-3.0.0.dist-info/LICENSE.txt
markdown_iconfonts-3.0.0.dist-info/METADATA
markdown_iconfonts-3.0.0.dist-info/WHEEL
markdown_iconfonts-3.0.0.dist-info/top_level.txt
markdown_iconfonts-3.0.0.dist-info/RECORD
