Metadata-Version: 2.1
Name: markdown-iconfonts
Version: 3.0.0
Summary: Easily display icon fonts in markdown.
Home-page: https://github.com/MadLittleMods/markdown-icons
Author: Eric Eastwood
License: UNKNOWN
Keywords: markdown,icons,fontawesome,bootstrap
Platform: UNKNOWN
Classifier: Development Status :: 3 - Alpha
Classifier: Environment :: Web Environment
Classifier: Intended Audience :: Developers
Classifier: License :: Other/Proprietary License
Classifier: Operating System :: OS Independent
Classifier: Programming Language :: Python :: 3
Requires-Dist: markdown
